ie_viz/__init__.py
ie_viz/static/color_code.json
ie_viz/static/js/App.js
ie_viz/static/js/DisplayTextBoxManager.js
ie_viz/static/js/FilterManager.js
ie_viz/static/js/TableManager.js
ie_viz/static/style.css
ie_viz/utilities.py
ie_viz-0.2.4.dist-info/METADATA
ie_viz-0.2.4.dist-info/WHEEL
ie_viz-0.2.4.dist-info/RECORD
