Metadata-Version: 2.1
Name: ie-viz
Version: 0.2.4
Summary: A simple visualization tool for NLP information extraction: Named entity recognition, Entity attribute extraction, and Relation extration.
License: MIT
Author: Enshuo (David) Hsu
Requires-Python: >=3.11,<4.0
Classifier: License :: OSI Approved :: MIT License
Classifier: Programming Language :: Python :: 3
Classifier: Programming Language :: Python :: 3.11
Classifier: Programming Language :: Python :: 3.12
Requires-Dist: flask (>=2.3)
Requires-Dist: flask-socketio (>=5.3.3)
